eaiesb/__init__.py
eaiesb/ingest.py
eaiesb/persist.py
eaiesb/transform.py
eaiesb-1.0.8.dist-info/METADATA
eaiesb-1.0.8.dist-info/WHEEL
eaiesb-1.0.8.dist-info/top_level.txt
eaiesb-1.0.8.dist-info/RECORD
