Metadata-Version: 2.1
Name: eaiesb
Version: 1.0.8
Summary: CSV Ingest-Transform-Persist
Home-page: https://www.eaiesb.com
Author: Akhil
Author-email: akhil.kumar@eaiesb.com
License: UNKNOWN
Platform: UNKNOWN
Requires-Dist: pyspark
